pySTid/__init__.py
pySTid/stidapi.py
pySTid/stidcore.py
pySTid/stidmobile-id-com-chain.pem
pySTid/stidresponse.py
pySTid-0.0.11.data/data/stidmobile-id-com-chain.pem
pySTid-0.0.11.dist-info/LICENSE.txt
pySTid-0.0.11.dist-info/METADATA
pySTid-0.0.11.dist-info/WHEEL
pySTid-0.0.11.dist-info/top_level.txt
pySTid-0.0.11.dist-info/RECORD
