Metadata-Version: 2.1
Name: pySTid
Version: 0.0.11
Summary: Python wrapper for using access the STid credential issuing server
Author: Sensor Access
Maintainer-email: admin@sensoraccess.co.uk
License-File: LICENSE.txt
